yawaei/__init__.py
yawaei/abc.py
yawaei/checkers.py
yawaei/constants.py
yawaei/intranet.py
yawaei-0.0.8.dist-info/LICENSE
yawaei-0.0.8.dist-info/METADATA
yawaei-0.0.8.dist-info/WHEEL
yawaei-0.0.8.dist-info/top_level.txt
yawaei-0.0.8.dist-info/RECORD
