Metadata-Version: 2.1
Name: yawaei
Version: 0.0.8
Summary: Yet Another Wrapper Around Epitech Intranet
Author-email: Aldon Julien <julien.aldon@epitech.eu>
License: Copyright (c) 2018 The Python Packaging Authority
Project-URL: Homepage, https://github.com/JulienAldon/YAWAEI
Project-URL: Bug Tracker, https://github.com/JulienAldon/YAWAEI/issues
Classifier: Development Status :: 3 - Alpha
Classifier: Programming Language :: Python :: 3
Classifier: License :: OSI Approved :: MIT License
Classifier: Operating System :: OS Independent
Requires-Python: >=3.9
License-File: LICENSE
